imgo/__init__.py
imgo/augtools.py
imgo/uptools.py
imgo-2.5.6.dist-info/LICENSE.txt
imgo-2.5.6.dist-info/METADATA
imgo-2.5.6.dist-info/WHEEL
imgo-2.5.6.dist-info/top_level.txt
imgo-2.5.6.dist-info/RECORD
