Metadata-Version: 2.1
Name: imgo
Version: 2.5.6
Summary: Image data processing and augmentation tools
Home-page: https://github.com/elbydata/imgo
Author: Elby Data
Author-email: info@elbydata.com
License: UNKNOWN
Platform: UNKNOWN
Classifier: Programming Language :: Python :: 3
Classifier: License :: OSI Approved :: MIT License
Classifier: Operating System :: OS Independent
Requires-Python: >=3.6
